pioemu/__init__.py
pioemu/conditions.py
pioemu/decoding/instruction_decoder.py
pioemu/emulation.py
pioemu/instruction.py
pioemu/instruction_decoder.py
pioemu/instructions/__init__.py
pioemu/instructions/pull.py
pioemu/instructions/push.py
pioemu/primitive_operations.py
pioemu/shift_register.py
pioemu/state.py
rp2040_pio_emulator-0.85.0.dist-info/METADATA
rp2040_pio_emulator-0.85.0.dist-info/WHEEL
rp2040_pio_emulator-0.85.0.dist-info/licenses/LICENSE
rp2040_pio_emulator-0.85.0.dist-info/RECORD
