Metadata-Version: 2.4
Name: rp2040-pio-emulator
Version: 0.85.0
Summary: RP2040 emulator for the testing and debugging of PIO programs
License-Expression: Apache-2.0
License-File: LICENSE
Keywords: rp2040,rp2,raspberry-pi-pico,testing,tdd,debugging
Author: Nathan Young
Requires-Python: >=3.10.18
Classifier: Programming Language :: Python :: 3
Classifier: Programming Language :: Python :: 3.11
Classifier: Programming Language :: Python :: 3.12
Classifier: Programming Language :: Python :: 3.13
Classifier: Programming Language :: Python :: 3.14
